PALS_pathway-1.5.2.data/scripts/run_pals.py
pals/GSEA.py
pals/ORA.py
pals/PLAGE.py
pals/__init__.py
pals/base.py
pals/common.py
pals/evaluation.py
pals/feature_extraction.py
pals/loader.py
pals/noise.py
pals/pimp_tools.py
pals/preprocessing.py
pals/reactome.py
pals/run_gui.py
pals/run_gui_gnps.py
pals/run_gui_pathway.py
pals/run_pals.py
pals/session_state.py
pals/data/COMPOUND.json.zip
pals/data/ChEBI.json.zip
pals/data/PiMP_KEGG.json.zip
pals/data/reactome/metabolic_pathways/COMPOUND/Arabidopsis thaliana.json.zip
pals/data/reactome/metabolic_pathways/COMPOUND/Bos taurus.json.zip
pals/data/reactome/metabolic_pathways/COMPOUND/Caenorhabditis elegans.json.zip
pals/data/reactome/metabolic_pathways/COMPOUND/Canis familiaris.json.zip
pals/data/reactome/metabolic_pathways/COMPOUND/Danio rerio.json.zip
pals/data/reactome/metabolic_pathways/COMPOUND/Dictyostelium discoideum.json.zip
pals/data/reactome/metabolic_pathways/COMPOUND/Drosophila melanogaster.json.zip
pals/data/reactome/metabolic_pathways/COMPOUND/Gallus gallus.json.zip
pals/data/reactome/metabolic_pathways/COMPOUND/Homo sapiens.json.zip
pals/data/reactome/metabolic_pathways/COMPOUND/Mus musculus.json.zip
pals/data/reactome/metabolic_pathways/COMPOUND/Oryza sativa.json.zip
pals/data/reactome/metabolic_pathways/COMPOUND/Plasmodium falciparum.json.zip
pals/data/reactome/metabolic_pathways/COMPOUND/Rattus norvegicus.json.zip
pals/data/reactome/metabolic_pathways/COMPOUND/Saccharomyces cerevisiae.json.zip
pals/data/reactome/metabolic_pathways/COMPOUND/Schizosaccharomyces pombe.json.zip
pals/data/reactome/metabolic_pathways/COMPOUND/Sus scrofa.json.zip
pals/data/reactome/metabolic_pathways/COMPOUND/Taeniopygia guttata.json.zip
pals/data/reactome/metabolic_pathways/COMPOUND/Xenopus tropicalis.json.zip
pals/data/reactome/metabolic_pathways/ChEBI/Arabidopsis thaliana.json.zip
pals/data/reactome/metabolic_pathways/ChEBI/Bos taurus.json.zip
pals/data/reactome/metabolic_pathways/ChEBI/Caenorhabditis elegans.json.zip
PALS_pathway-1.5.2.dist-info/LICENSE
PALS_pathway-1.5.2.dist-info/METADATA
PALS_pathway-1.5.2.dist-info/WHEEL
PALS_pathway-1.5.2.dist-info/entry_points.txt
PALS_pathway-1.5.2.dist-info/top_level.txt
PALS_pathway-1.5.2.dist-info/RECORD
