Metadata-Version: 2.1
Name: PALS-pathway
Version: 1.5.2
Summary: A Python tool to rank significantly-changing metabolite sets
Home-page: https://github.com/glasgowcompbio/PALS
Author: Joe Wandy
Author-email: joe.wandy@glasgow.ac.uk
License: UNKNOWN
Platform: UNKNOWN
Classifier: Programming Language :: Python :: 3
Classifier: License :: OSI Approved :: MIT License
Classifier: Operating System :: OS Independent
Requires-Python: >=3.6
Requires-Dist: numpy
Requires-Dist: scipy
Requires-Dist: pandas
Requires-Dist: seaborn
Requires-Dist: scikit-learn
Requires-Dist: matplotlib
Requires-Dist: statsmodels
Requires-Dist: loguru
Requires-Dist: requests
Requires-Dist: neo4j-driver
Requires-Dist: gseapy (==0.9.16)
Requires-Dist: streamlit
Requires-Dist: tqdm
Requires-Dist: pillow
